li_queens/__init__.py
li_queens-0.1.0.dist-info/METADATA
li_queens-0.1.0.dist-info/WHEEL
li_queens-0.1.0.dist-info/entry_points.txt
li_queens-0.1.0.dist-info/RECORD
