Metadata-Version: 2.4
Name: li_queens
Version: 0.1.0
Summary: Solve a LinkedIn Queens puzzle in an image.
Author-email: Rodrigo Girão Serrão <5621605+rodrigogiraoserrao@users.noreply.github.com>
Requires-Python: >=3.13
Requires-Dist: click>=8.1.8
Requires-Dist: pillow>=11.1.0
